{
  "0": "affirm",
  "1": "ask_center_details",
  "2": "ask_contact",
  "3": "ask_db_status",
  "4": "ask_features",
  "5": "ask_how_to_run",
  "6": "ask_notifications",
  "7": "ask_pending_requests",
  "8": "ask_relief_centers",
  "9": "ask_relief_prediction",
  "10": "ask_resources",
  "11": "ask_roles",
  "12": "ask_system_stats",
  "13": "ask_tech_stack",
  "14": "ask_user_requests",
  "15": "ask_volunteers",
  "16": "ask_weather",
  "17": "ask_what_is_relieflink",
  "18": "bot_challenge",
  "19": "deny",
  "20": "goodbye",
  "21": "greet",
  "22": "mood_great",
  "23": "mood_unhappy"
}